README.md
setup.py
rcon_server/__init__.py
rcon_server/rcon_client.py
rcon_server/rcon_client_test.py
rcon_server/rcon_connection.py
rcon_server/rcon_message.py
rcon_server/rcon_packet.py
rcon_server/rcon_server.py
rcon_server/test_rcon_client.py
rcon_server/test_rcon_connection.py
rcon_server/test_rcon_message.py
rcon_server/test_rcon_packet.py
rcon_server/test_util.py
rcon_server/util.py
rcon_server.egg-info/PKG-INFO
rcon_server.egg-info/SOURCES.txt
rcon_server.egg-info/dependency_links.txt
rcon_server.egg-info/top_level.txt