Metadata-Version: 2.1
Name: rcon-server
Version: 0.1.2
Summary: a server side implementaiton of the RCON Protocol.
Home-page: https://github.com/991jo/rcon-server/
Author: Johannes Erwerle
Author-email: johannes.erwerle@googlemail.com
License: UNKNOWN
Platform: UNKNOWN
Classifier: Programming Language :: Python :: 3.5
Classifier: Operating System :: OS Independent
